NJUlogin/__init__.py
NJUlogin/__main__.py
NJUlogin/base.py
NJUlogin/captchaOCR/__init__.py
NJUlogin/captchaOCR/nju_captcha.onnx
NJUlogin/captchaOCR/ocr.py
NJUlogin/captchaOCR/utils.py
NJUlogin/pwdLogin.py
NJUlogin/QRlogin.py
NJUlogin/utils/__init__.py
NJUlogin/utils/config.py
NJUlogin/utils/get_post.py
NJUlogin/utils/urls.py
njulogin-3.5.1.dist-info/entry_points.txt
njulogin-3.5.1.dist-info/LICENSE
njulogin-3.5.1.dist-info/METADATA
njulogin-3.5.1.dist-info/WHEEL
njulogin-3.5.1.dist-info/RECORD
