Metadata-Version: 2.1
Name: NJUlogin
Version: 3.5.1
Summary: The Nanjing University login module, which can be used to login to the various campus web sites
Home-page: https://github.com/Do1e/NJUlogin
License: MIT
Author: Do1e
Author-email: dpj.email@qq.com
Requires-Python: >=3.10,<4.0
Classifier: License :: OSI Approved :: MIT License
Classifier: Operating System :: OS Independent
Classifier: Programming Language :: Python :: 3
Classifier: Programming Language :: Python :: 3.10
Classifier: Programming Language :: Python :: 3.11
Classifier: Programming Language :: Python :: 3.12
Classifier: Programming Language :: Python :: 3.13
Requires-Dist: cryptography (>=43.0.0)
Requires-Dist: lxml (>=5.3.0)
Requires-Dist: numpy (>=2.0.0)
Requires-Dist: onnxruntime (>=1.20.0)
Requires-Dist: pillow (>=11.0.0)
Requires-Dist: pycryptodome (>=3.21.0)
Requires-Dist: requests (>=2.32.0)
Project-URL: Repository, https://github.com/Do1e/NJUlogin
